unmanned_enterprise/__init__.py
unmanned_enterprise/address/__init__.py
unmanned_enterprise/address/address.py
unmanned_enterprise/address/department.py
unmanned_enterprise/ai/__init__.py
unmanned_enterprise/ai/llm/__init__.py
unmanned_enterprise/ai/llm/chat.py
unmanned_enterprise/ai/llm/text_to_image_prompt.py
unmanned_enterprise/api/__init__.py
unmanned_enterprise/api/lib/__init__.py
unmanned_enterprise/api/lib/tab.py
unmanned_enterprise/api/lib/view.py
unmanned_enterprise/api/lib/web.py
unmanned_enterprise/api/lib/window.py
unmanned_enterprise/member/__init__.py
unmanned_enterprise/member/chat.py
unmanned_enterprise/member/chat_base.py
unmanned_enterprise/member/history.py
unmanned_enterprise/member/interrupt.py
unmanned_enterprise/member/lib.py
unmanned_enterprise/member/message.py
unmanned_enterprise/member/prompt.jinja
unmanned_enterprise/member/prompt.py
unmanned_enterprise/reference/__init__.py
unmanned_enterprise/reference/mcp.py
unmanned_enterprise/reference/member.py
unmanned_enterprise/reference/tool.py
unmanned_enterprise/reference/workflow.py
unmanned_enterprise/reference/lib/__init__.py
unmanned_enterprise/reference/lib/call_func.py
unmanned_enterprise/reference/lib/change_directory.py
unmanned_enterprise/tool/__init__.py
unmanned_enterprise/tool/tool_decorator.py
unmanned_enterprise/ui/__init__.py
unmanned_enterprise/ui/base.py
unmanned_enterprise/ui/color.py
unmanned_enterprise/ui/typ.py
unmanned_enterprise/ui/ui_def.py
unmanned_enterprise/utils/__init__.py
unmanned_enterprise/utils/arg.py
unmanned_enterprise/utils/env.py
unmanned_enterprise/utils/json.py
unmanned_enterprise/utils/process.py
unmanned_enterprise/utils/socket.py
unmanned_enterprise/utils/text_or_file.py
unmanned_enterprise/utils/web.py
unmanned_enterprise-0.0.93.dist-info/LICENSE
unmanned_enterprise-0.0.93.dist-info/METADATA
unmanned_enterprise-0.0.93.dist-info/WHEEL
unmanned_enterprise-0.0.93.dist-info/top_level.txt
unmanned_enterprise-0.0.93.dist-info/RECORD
