Metadata-Version: 2.1
Name: unmanned-enterprise
Version: 0.0.93
Summary: Package for unmanned_enterprise only!
Author: Jie Xiong
Author-email: yuanjiexiong@gmail.com
Classifier: Programming Language :: Python :: 3
Classifier: Operating System :: OS Independent
Requires-Python: >=3.9
License-File: LICENSE
